bonggoQuery/__init__.py
bonggoQuery/assets/logo.png
bonggoQuery-2.0.2.3.dist-info/METADATA
bonggoQuery-2.0.2.3.dist-info/WHEEL
bonggoQuery-2.0.2.3.dist-info/top_level.txt
bonggoQuery-2.0.2.3.dist-info/RECORD
