Metadata-Version: 2.1
Name: bonggoQuery
Version: 2.0.2.3
Summary: A package that helps you perform various operations, especially for building virtual assistants.
Home-page: https://github.com/SudipBera083
Author: Sudip Bera
Author-email: sudipbera083@gmail.com
License: MIT
Project-URL: Bug Tracker, https://github.com/SudipBera083/issues
Project-URL: Source Code, https://github.com/SudipBera083/BonggoQuery
Keywords: virtual assistant query voice python
Classifier: Programming Language :: Python :: 3
Classifier: License :: OSI Approved :: MIT License
Classifier: Operating System :: OS Independent
Requires-Python: >=3.6
Requires-Dist: wolframalpha
Requires-Dist: pyttsx3
Requires-Dist: SpeechRecognition
Requires-Dist: wikipedia
